{
  "metadata": {
    "module": "Harvesting Interval",
    "activitySourceFile": "Harvesting Interval.xlsx",
    "referenceTemplateFile": "Harvesting_Interval_.xlsm",
    "sourceDescription": "QC and C1 harvesting activity extracted from the company source system after manual filtering.",
    "baseDate": "2026-03-31",
    "startDate": "2026-04-01",
    "lastActivityDate": "2026-06-19",
    "defaultMonth": "2026-04",
    "availableMonths": [
      "2026-04",
      "2026-05",
      "2026-06"
    ],
    "templateDescription": "HD screenshot-aligned D1-D9 harvesting interval report template."
  },
  "fields": [
    {
      "id": "D1-01-02D1",
      "field": "02D1",
      "block": "D1",
      "hectares": 38.17,
      "blockHectares": 187.84,
      "baseInterval": 20,
      "bfDisplay": "20",
      "hasReferenceBaseline": true
    },
    {
      "id": "D1-02-2009D",
      "field": "2009D",
      "block": "D1",
      "hectares": 77.39,
      "blockHectares": 187.84,
      "baseInterval": 20,
      "bfDisplay": "20",
      "hasReferenceBaseline": true
    },
    {
      "id": "D1-03-P06C",
      "field": "P06C",
      "block": "D1",
      "hectares": 61.49,
      "blockHectares": 187.84,
      "baseInterval": 20,
      "bfDisplay": "20",
      "hasReferenceBaseline": true
    },
    {
      "id": "D1-04-2023D",
      "field": "2023D",
      "block": "D1",
      "hectares": 10.79,
      "blockHectares": 187.84,
      "baseInterval": 16,
      "bfDisplay": "16",
      "hasReferenceBaseline": true
    },
    {
      "id": "D2-05-2009C",
      "field": "2009C",
      "block": "D2",
      "hectares": 69.09,
      "blockHectares": 188.85,
      "baseInterval": 19,
      "bfDisplay": "19",
      "hasReferenceBaseline": true
    },
    {
      "id": "D2-06-2014C",
      "field": "2014C",
      "block": "D2",
      "hectares": 7.4,
      "blockHectares": 188.85,
      "baseInterval": 19,
      "bfDisplay": "19",
      "hasReferenceBaseline": true
    },
    {
      "id": "D2-07-08C1",
      "field": "08C1",
      "block": "D2",
      "hectares": 36.26,
      "blockHectares": 188.85,
      "baseInterval": 18,
      "bfDisplay": "18",
      "hasReferenceBaseline": true
    },
    {
      "id": "D2-08-05C1",
      "field": "05C1",
      "block": "D2",
      "hectares": 44.9,
      "blockHectares": 188.85,
      "baseInterval": 19,
      "bfDisplay": "19",
      "hasReferenceBaseline": true
    },
    {
      "id": "D2-09-2014A",
      "field": "2014A",
      "block": "D2",
      "hectares": 31.2,
      "blockHectares": 188.85,
      "baseInterval": 18,
      "bfDisplay": "18",
      "hasReferenceBaseline": true
    },
    {
      "id": "D3-10-2014A",
      "field": "2014A",
      "block": "D3",
      "hectares": 30.69,
      "blockHectares": 188.82,
      "baseInterval": 18,
      "bfDisplay": "18",
      "hasReferenceBaseline": true
    },
    {
      "id": "D3-11-2012B",
      "field": "2012B",
      "block": "D3",
      "hectares": 66.77,
      "blockHectares": 188.82,
      "baseInterval": 17,
      "bfDisplay": "17",
      "hasReferenceBaseline": true
    },
    {
      "id": "D3-12-2012A",
      "field": "2012A",
      "block": "D3",
      "hectares": 65.06,
      "blockHectares": 188.82,
      "baseInterval": 17,
      "bfDisplay": "17",
      "hasReferenceBaseline": true
    },
    {
      "id": "D3-13-2009C1",
      "field": "2009C1",
      "block": "D3",
      "hectares": 26.3,
      "blockHectares": 188.82,
      "baseInterval": 17,
      "bfDisplay": "17",
      "hasReferenceBaseline": true
    },
    {
      "id": "D4-14-2009C1",
      "field": "2009C1",
      "block": "D4",
      "hectares": 49.85,
      "blockHectares": 188.86,
      "baseInterval": 16,
      "bfDisplay": "16",
      "hasReferenceBaseline": true
    },
    {
      "id": "D4-15-2017A",
      "field": "2017A",
      "block": "D4",
      "hectares": 99.51,
      "blockHectares": 188.86,
      "baseInterval": 16,
      "bfDisplay": "16",
      "hasReferenceBaseline": true
    },
    {
      "id": "D4-16-2019A",
      "field": "2019A",
      "block": "D4",
      "hectares": 39.5,
      "blockHectares": 188.86,
      "baseInterval": 7,
      "bfDisplay": "7",
      "hasReferenceBaseline": true
    },
    {
      "id": "D5-17-2019A",
      "field": "2019A",
      "block": "D5",
      "hectares": 6.95,
      "blockHectares": 184.77,
      "baseInterval": 7,
      "bfDisplay": "7",
      "hasReferenceBaseline": true
    },
    {
      "id": "D5-18-2019B",
      "field": "2019B",
      "block": "D5",
      "hectares": 24.33,
      "blockHectares": 184.77,
      "baseInterval": 6,
      "bfDisplay": "6",
      "hasReferenceBaseline": true
    },
    {
      "id": "D5-19-2019B",
      "field": "2019B",
      "block": "D5",
      "hectares": 24.33,
      "blockHectares": 184.77,
      "baseInterval": 6,
      "bfDisplay": "6",
      "hasReferenceBaseline": true
    },
    {
      "id": "D5-20-2017C",
      "field": "2017C",
      "block": "D5",
      "hectares": 107.16,
      "blockHectares": 184.77,
      "baseInterval": 6,
      "bfDisplay": "6",
      "hasReferenceBaseline": true
    },
    {
      "id": "D5-21-2017B",
      "field": "2017B",
      "block": "D5",
      "hectares": 22.0,
      "blockHectares": 184.77,
      "baseInterval": 7,
      "bfDisplay": "7",
      "hasReferenceBaseline": true
    },
    {
      "id": "D6-22-2017B",
      "field": "2017B",
      "block": "D6",
      "hectares": 75.36,
      "blockHectares": 187.98,
      "baseInterval": 7,
      "bfDisplay": "7",
      "hasReferenceBaseline": true
    },
    {
      "id": "D6-23-07B3A",
      "field": "07B3A",
      "block": "D6",
      "hectares": 86.62,
      "blockHectares": 187.98,
      "baseInterval": 5,
      "bfDisplay": "5",
      "hasReferenceBaseline": true
    },
    {
      "id": "D6-24-07B3",
      "field": "07B3",
      "block": "D6",
      "hectares": 26.0,
      "blockHectares": 187.98,
      "baseInterval": 5,
      "bfDisplay": "5",
      "hasReferenceBaseline": true
    },
    {
      "id": "D7-25-07B3",
      "field": "07B3",
      "block": "D7",
      "hectares": 31.74,
      "blockHectares": 186.73,
      "baseInterval": 4,
      "bfDisplay": "4",
      "hasReferenceBaseline": true
    },
    {
      "id": "D7-26-07B3B",
      "field": "07B3B",
      "block": "D7",
      "hectares": 48.96,
      "blockHectares": 186.73,
      "baseInterval": 4,
      "bfDisplay": "4",
      "hasReferenceBaseline": true
    },
    {
      "id": "D7-27-2018B1",
      "field": "2018B1",
      "block": "D7",
      "hectares": 51.93,
      "blockHectares": 186.73,
      "baseInterval": 4,
      "bfDisplay": "4",
      "hasReferenceBaseline": true
    },
    {
      "id": "D7-28-07B1",
      "field": "07B1",
      "block": "D7",
      "hectares": 54.1,
      "blockHectares": 186.73,
      "baseInterval": 2,
      "bfDisplay": "H2",
      "hasReferenceBaseline": true
    },
    {
      "id": "D8-29-07B1",
      "field": "07B1",
      "block": "D8",
      "hectares": 7.1,
      "blockHectares": 188.99,
      "baseInterval": 2,
      "bfDisplay": "2",
      "hasReferenceBaseline": true
    },
    {
      "id": "D8-30-2016B",
      "field": "2016B",
      "block": "D8",
      "hectares": 75.29,
      "blockHectares": 188.99,
      "baseInterval": 3,
      "bfDisplay": "3",
      "hasReferenceBaseline": true
    },
    {
      "id": "D8-31-2015B",
      "field": "2015B",
      "block": "D8",
      "hectares": 68.8,
      "blockHectares": 188.99,
      "baseInterval": 2,
      "bfDisplay": "H2",
      "hasReferenceBaseline": true
    },
    {
      "id": "D8-32-P06B",
      "field": "P06B",
      "block": "D8",
      "hectares": 37.8,
      "blockHectares": 188.99,
      "baseInterval": 3,
      "bfDisplay": "3",
      "hasReferenceBaseline": true
    },
    {
      "id": "D9-33-P06B",
      "field": "P06B",
      "block": "D9",
      "hectares": 34.12,
      "blockHectares": 189.53,
      "baseInterval": 1,
      "bfDisplay": "H1",
      "hasReferenceBaseline": true
    },
    {
      "id": "D9-34-2015E",
      "field": "2015E",
      "block": "D9",
      "hectares": 56.0,
      "blockHectares": 189.53,
      "baseInterval": 21,
      "bfDisplay": "21",
      "hasReferenceBaseline": true
    },
    {
      "id": "D9-35-2018A",
      "field": "2018A",
      "block": "D9",
      "hectares": 99.41,
      "blockHectares": 189.53,
      "baseInterval": 1,
      "bfDisplay": "H1",
      "hasReferenceBaseline": true
    }
  ],
  "activityByField": {
    "02D1": [
      "2026-04-02",
      "2026-04-14",
      "2026-04-15",
      "2026-04-16",
      "2026-04-26",
      "2026-05-09",
      "2026-05-11",
      "2026-05-12",
      "2026-05-22",
      "2026-05-23",
      "2026-05-25",
      "2026-06-05",
      "2026-06-06",
      "2026-06-08",
      "2026-06-18"
    ],
    "05C1": [
      "2026-04-03",
      "2026-04-15",
      "2026-04-16",
      "2026-04-17",
      "2026-04-27",
      "2026-05-12",
      "2026-05-13",
      "2026-05-25",
      "2026-05-26",
      "2026-06-08",
      "2026-06-19"
    ],
    "07B1": [
      "2026-04-11",
      "2026-04-12",
      "2026-04-13",
      "2026-04-22",
      "2026-04-23",
      "2026-04-24",
      "2026-05-06",
      "2026-05-07",
      "2026-05-20",
      "2026-05-21",
      "2026-06-03",
      "2026-06-15",
      "2026-06-16"
    ],
    "07B3": [
      "2026-04-10",
      "2026-04-11",
      "2026-04-21",
      "2026-04-22",
      "2026-05-05",
      "2026-05-18",
      "2026-05-19",
      "2026-05-31",
      "2026-06-02",
      "2026-06-13",
      "2026-06-14"
    ],
    "07B3A": [
      "2026-04-10",
      "2026-04-11",
      "2026-04-21",
      "2026-04-22",
      "2026-05-04",
      "2026-05-05",
      "2026-05-17",
      "2026-05-19",
      "2026-05-20",
      "2026-05-30",
      "2026-05-31",
      "2026-06-02",
      "2026-06-12",
      "2026-06-13",
      "2026-06-14"
    ],
    "07B3B": [
      "2026-04-10",
      "2026-04-11",
      "2026-04-22",
      "2026-04-23",
      "2026-05-05",
      "2026-05-06",
      "2026-05-18",
      "2026-05-19",
      "2026-05-20",
      "2026-05-31",
      "2026-06-02",
      "2026-06-03",
      "2026-06-13",
      "2026-06-14",
      "2026-06-15"
    ],
    "08C1": [
      "2026-04-03",
      "2026-04-15",
      "2026-04-16",
      "2026-04-17",
      "2026-04-27",
      "2026-05-12",
      "2026-05-13",
      "2026-05-25",
      "2026-05-26",
      "2026-06-06",
      "2026-06-08",
      "2026-06-19"
    ],
    "2009C": [
      "2026-04-01",
      "2026-04-02",
      "2026-04-03",
      "2026-04-04",
      "2026-04-15",
      "2026-04-16",
      "2026-04-26",
      "2026-04-27",
      "2026-04-28",
      "2026-05-09",
      "2026-05-11",
      "2026-05-12",
      "2026-05-13",
      "2026-05-14",
      "2026-05-22",
      "2026-05-23",
      "2026-05-26",
      "2026-06-05",
      "2026-06-06",
      "2026-06-08",
      "2026-06-09",
      "2026-06-17",
      "2026-06-18"
    ],
    "2009C1": [
      "2026-04-06",
      "2026-04-07",
      "2026-04-08",
      "2026-04-17",
      "2026-04-18",
      "2026-04-20",
      "2026-04-28",
      "2026-04-29",
      "2026-04-30",
      "2026-05-14",
      "2026-05-15",
      "2026-05-16",
      "2026-05-28",
      "2026-05-29",
      "2026-06-09",
      "2026-06-10",
      "2026-06-11"
    ],
    "2009D": [
      "2026-04-01",
      "2026-04-02",
      "2026-04-14",
      "2026-04-15",
      "2026-04-16",
      "2026-04-26",
      "2026-05-09",
      "2026-05-11",
      "2026-05-12",
      "2026-05-22",
      "2026-05-23",
      "2026-05-25",
      "2026-06-05",
      "2026-06-06",
      "2026-06-08",
      "2026-06-18"
    ],
    "2012A": [
      "2026-04-04",
      "2026-04-06",
      "2026-04-07",
      "2026-04-16",
      "2026-04-17",
      "2026-04-18",
      "2026-04-28",
      "2026-04-29",
      "2026-05-13",
      "2026-05-14",
      "2026-05-15",
      "2026-05-26",
      "2026-05-28",
      "2026-06-09",
      "2026-06-10"
    ],
    "2012B": [
      "2026-04-06",
      "2026-04-16",
      "2026-04-17",
      "2026-04-18",
      "2026-04-28",
      "2026-04-29",
      "2026-05-13",
      "2026-05-14",
      "2026-05-15",
      "2026-05-25",
      "2026-05-26",
      "2026-05-28",
      "2026-06-08",
      "2026-06-09",
      "2026-06-10"
    ],
    "2014A": [
      "2026-04-03",
      "2026-04-04",
      "2026-04-06",
      "2026-04-16",
      "2026-04-17",
      "2026-04-27",
      "2026-04-28",
      "2026-05-12",
      "2026-05-13",
      "2026-05-14",
      "2026-05-25",
      "2026-05-26",
      "2026-05-28",
      "2026-06-08",
      "2026-06-09",
      "2026-06-10"
    ],
    "2014C": [
      "2026-04-02",
      "2026-04-16",
      "2026-04-26",
      "2026-05-11",
      "2026-05-12",
      "2026-05-23",
      "2026-06-06"
    ],
    "2015B": [
      "2026-04-12",
      "2026-04-13",
      "2026-04-23",
      "2026-04-24",
      "2026-05-06",
      "2026-05-07",
      "2026-05-08",
      "2026-05-09",
      "2026-05-19",
      "2026-05-20",
      "2026-05-22",
      "2026-06-02",
      "2026-06-03",
      "2026-06-04",
      "2026-06-15",
      "2026-06-16"
    ],
    "2015E": [
      "2026-04-01",
      "2026-04-02",
      "2026-04-13",
      "2026-04-14",
      "2026-04-24",
      "2026-04-25",
      "2026-05-08",
      "2026-05-09",
      "2026-05-11",
      "2026-05-21",
      "2026-05-22",
      "2026-05-23",
      "2026-06-04",
      "2026-06-05",
      "2026-06-16",
      "2026-06-17",
      "2026-06-18"
    ],
    "2016B": [
      "2026-04-12",
      "2026-04-13",
      "2026-04-23",
      "2026-04-24",
      "2026-05-06",
      "2026-05-08",
      "2026-05-09",
      "2026-05-19",
      "2026-05-21",
      "2026-05-22",
      "2026-06-02",
      "2026-06-04",
      "2026-06-14",
      "2026-06-16",
      "2026-06-17",
      "2026-06-18"
    ],
    "2017A": [
      "2026-04-07",
      "2026-04-08",
      "2026-04-17",
      "2026-04-18",
      "2026-04-20",
      "2026-04-21",
      "2026-04-29",
      "2026-04-30",
      "2026-05-02",
      "2026-05-14",
      "2026-05-15",
      "2026-05-16",
      "2026-05-17",
      "2026-05-28",
      "2026-05-29",
      "2026-05-30",
      "2026-06-10",
      "2026-06-11",
      "2026-06-12"
    ],
    "2017B": [
      "2026-04-08",
      "2026-04-09",
      "2026-04-18",
      "2026-04-20",
      "2026-04-21",
      "2026-04-30",
      "2026-05-02",
      "2026-05-04",
      "2026-05-15",
      "2026-05-16",
      "2026-05-17",
      "2026-05-29",
      "2026-05-30",
      "2026-06-10",
      "2026-06-11",
      "2026-06-12",
      "2026-06-13"
    ],
    "2017C": [
      "2026-04-09",
      "2026-04-10",
      "2026-04-20",
      "2026-04-21",
      "2026-04-22",
      "2026-04-30",
      "2026-05-02",
      "2026-05-04",
      "2026-05-16",
      "2026-05-17",
      "2026-05-18",
      "2026-05-19",
      "2026-05-21",
      "2026-05-30",
      "2026-05-31",
      "2026-06-02",
      "2026-06-12",
      "2026-06-13"
    ],
    "2018A": [
      "2026-04-01",
      "2026-04-13",
      "2026-04-14",
      "2026-04-23",
      "2026-04-24",
      "2026-04-25",
      "2026-05-07",
      "2026-05-08",
      "2026-05-09",
      "2026-05-20",
      "2026-05-21",
      "2026-05-23",
      "2026-06-03",
      "2026-06-04",
      "2026-06-05",
      "2026-06-15",
      "2026-06-16",
      "2026-06-17"
    ],
    "2018B1": [
      "2026-04-11",
      "2026-04-12",
      "2026-04-22",
      "2026-04-23",
      "2026-05-05",
      "2026-05-06",
      "2026-05-18",
      "2026-05-19",
      "2026-05-20",
      "2026-05-21",
      "2026-05-31",
      "2026-06-02",
      "2026-06-03",
      "2026-06-14",
      "2026-06-15"
    ],
    "2019A": [
      "2026-04-09",
      "2026-04-20",
      "2026-04-21",
      "2026-05-02",
      "2026-05-04",
      "2026-05-16",
      "2026-05-17",
      "2026-05-18",
      "2026-05-29",
      "2026-05-30",
      "2026-05-31",
      "2026-06-11",
      "2026-06-12",
      "2026-06-13"
    ],
    "2019B": [
      "2026-04-09",
      "2026-04-20",
      "2026-04-21",
      "2026-05-02",
      "2026-05-04",
      "2026-05-16",
      "2026-05-17",
      "2026-05-18",
      "2026-05-29",
      "2026-05-30",
      "2026-05-31",
      "2026-06-02",
      "2026-06-11",
      "2026-06-12",
      "2026-06-13"
    ],
    "2023D": [
      "2026-04-02",
      "2026-04-03",
      "2026-04-10",
      "2026-04-11",
      "2026-04-20",
      "2026-04-21",
      "2026-04-22",
      "2026-04-23",
      "2026-05-02",
      "2026-05-04",
      "2026-05-16",
      "2026-05-17",
      "2026-05-18",
      "2026-05-25",
      "2026-05-26",
      "2026-06-05",
      "2026-06-06",
      "2026-06-16",
      "2026-06-17"
    ],
    "P06B": [
      "2026-04-11",
      "2026-04-14",
      "2026-04-23",
      "2026-04-24",
      "2026-04-25",
      "2026-05-07",
      "2026-05-08",
      "2026-05-09",
      "2026-05-21",
      "2026-05-22",
      "2026-06-04",
      "2026-06-05",
      "2026-06-16",
      "2026-06-18"
    ],
    "P06C": [
      "2026-04-01",
      "2026-04-02",
      "2026-04-03",
      "2026-04-04",
      "2026-04-14",
      "2026-04-15",
      "2026-04-16",
      "2026-04-25",
      "2026-04-26",
      "2026-04-27",
      "2026-05-09",
      "2026-05-11",
      "2026-05-12",
      "2026-05-13",
      "2026-05-22",
      "2026-05-23",
      "2026-05-25",
      "2026-06-05",
      "2026-06-06",
      "2026-06-08",
      "2026-06-17",
      "2026-06-18",
      "2026-06-19"
    ]
  }
}
